{
    "oak": {
        "x": [0.75, 0.078, 0.0, 0.2, 0.5, 0.5, 0.333, 0.755, 1.0, 0.636],
        "w": [0.5, 0.5, 0.5, 0.5, 0.5, 0.5, 0.5, 0.5, 0.5, 0.5],
        "count": 10
    },
    "vanilla": {
        "x": [0.667, 0.75, 0.111, 0.167, 0.267, 1.0],
        "w": [0.5, 0.5, 0.5, 0.5, 0.1, 0.5],
        "count": 6
    },
    "tobacco": {
        "x": [0.109, 0.077, 0.614, 0.0, 0.614],
        "w": [0.5, 0.5, 0.5, 0.5, 0.5],
        "count": 4
    },
    "cherry": {
        "x": [0.047, 0.0, 0.0, 0.214, 0.467],
        "w": [0.5, 0.5, 0.5, 0.2, 0.5],
        "count": 5
    },
    "leather": {
        "x": [0.486, 0.775, 0.486],
        "w": [0.5, 0.5, 0.5],
        "count": 3
    },
    "chocolate": {
        "x": [1.0, 0.733, 0.667, 0.438],
        "w": [0.5, 0.5, 0.5, 0.5],
        "count": 4
    },
    "raspberry": {
        "x": [0.778, 0.262, 1.0, 0.1],
        "w": [0.5, 0.5, 0.5, 0.5],
        "count": 3
    },
    "fruity": {
        "x": [1.0, 0.0],
        "w": [0.5, 0.5],
        "count": 2
    }
}