{
    "oak": {
        "x": [0.502, 0.529, 0.581, 0.0, 1.0, 0.789, 0.0, 0.969, 0.077, 0.087, 0.0, 0.038, 0.25, 0.895, 0.538, 0.75, 0.333],
        "w": [0.5, 0.5, 0.5, 0.5, 0.5, 0.5, 0.5, 0.5, 0.5, 0.5, 0.5, 0.5, 0.5, 0.5, 0.5, 0.5, 0.5],
        "count": 13
    },
    "tobacco": {
        "x": [0.28, 0.187, 0.565, 0.556, 0.938, 0.591, 0.174, 1.0, 0.346, 0.162, 0.794, 0.374, 0.754],
        "w": [0.3, 0.5, 0.5, 0.5, 0.5, 0.5, 0.5, 0.5, 0.5, 0.5, 0.5, 0.5, 0.5],
        "count": 11
    },
    "fruity": {
        "x": [0.712, 0.575, 1.0, 0.75, 0.632],
        "w": [0.5, 0.5, 0.5, 0.5, 0.5],
        "count": 5
    },
    "cherry": {
        "x": [0.19, 0.58, 0.364, 0.125, 0.75, 0.3, 0.312, 0.524, 0.619, 0.762, 0.25, 0.423, 0.677, 0.5, 0.5, 0.25, 0.4],
        "w": [0.57, 0.57, 0.57, 0.57, 0.57, 0.57, 0.57, 0.57, 0.57, 0.57, 0.57, 0.57, 0.57, 0.57, 0.57, 0.57, 0.57],
        "count": 15
    },
    "raisin": {
        "x": [0.572, 0.261],
        "w": [0.5, 0.5],
        "count": 2
    },
    "leather": {
        "x": [0.549, 0.632, 0.5, 0.755, 0.75, 0.853, 0.6],
        "w": [0.5, 0.5, 0.5, 0.5, 0.2, 0.5, 0.5],
        "count": 7
    },
    "chocolate": {
        "x": [0.165, 0.675, 0.0, 0.762, 0.0, 0.5, 0.71, 0.742, 0.806, 1.0, 0.5, 1.0, 0.8],
        "w": [0.5, 0.5, 0.5, 0.5, 0.5, 0.5, 0.5, 0.5, 0.5, 0.5, 0.5, 0.5, 0.5],
        "count": 12
    },
    "vanilla": {
        "x": [0.65, 0.621, 1.0, 1.0, 0.75],
        "w": [0.5, 0.1, 0.5, 0.5, 0.5],
        "count": 5
    },
    "plum": {
        "x": [0.1, 0.0, 0.571, 0.391, 0.471, 0.5, 0.5],
        "w": [0.5, 0.5, 0.5, 0.5, 0.5, 0.5, 0.5],
        "count": 7
    },
    "currant": {
        "x": [0.25, 0.4, 0.412],
        "w": [0.57, 0.57, 0.57],
        "count": 2
    },
    "pepper": {
        "x": [0.325, 0.115, 0.867, 0.714],
        "w": [0.5, 0.5, 0.5, 0.5],
        "count": 4
    },
    "blackberry": {
        "x": [1.0, 0.629, 1.0, 0.25],
        "w": [0.57, 0.57, 0.57, 0.57],
        "count": 4
    },
    "smoke": {
        "x": [0.1, 1.0, 0.095, 0.673, 0.75, 0.269, 1.0, 0.799],
        "w": [0.5, 0.5, 0.5, 0.5, 0.5, 0.5, 0.5, 0.5],
        "count": 8
    },
    "red fruit": {
        "x": [0.111, 0.857, 0.286],
        "w": [0.5, 0.5, 0.5],
        "count": 3
    },
    "floral": {
        "x": [0.286, 0.143, 0.714],
        "w": [0.5, 0.5, 0.5],
        "count": 2
    },
    "earthy": {
        "x": [0.918, 0.559],
        "w": [0.5, 0.5],
        "count": 2
    },
    "liquorice": {
        "x": [0.277, 0.735],
        "w": [0.5, 0.5],
        "count": 2
    },
    "violet": {
        "x": [0.155, 0.733],
        "w": [0.5, 0.5],
        "count": 2
    }
}