{
    "lychee": {
        "x": [0.127, 0.719],
        "w": [0.5, 0.5],
        "count": 2
    },
    "beeswax": {
        "x": [0.236, 0.143],
        "w": [0.5, 0.5],
        "count": 2
    },
    "tropical": {
        "x": [0.036, 0.227],
        "w": [0.5, 0.5],
        "count": 2
    },
    "honey": {
        "x": [0.0, 0.0, 0.833, 0.4, 0.0, 0.656, 0.879, 0.0, 0.12, 0.161, 0.5, 0.636],
        "w": [0.5, 0.5, 0.5, 0.5, 0.5, 0.5, 0.15, 0.5, 0.5, 0.5, 0.5, 0.5],
        "count": 10
    },
    "pineapple": {
        "x": [0.25, 0.167, 0.6, 0.688, 1.0],
        "w": [0.5, 0.5, 0.5, 0.5, 0.5],
        "count": 5
    },
    "mineral": {
        "x": [1.0, 0.083, 0.2, 0.42, 0.375, 0.864],
        "w": [0.5, 0.5, 0.5, 0.5, 0.5, 0.5],
        "count": 6
    },
    "apricot": {
        "x": [0.25, 1.0, 1.0, 0.343, 0.143, 0.75, 0.277, 0.936],
        "w": [0.5, 0.5, 0.5, 0.5, 0.5, 0.5, 0.5, 0.5],
        "count": 6
    },
    "peach": {
        "x": [0.215, 0.771, 0.72, 0.682, 0.441, 0.269, 0.727, 0.213, 0.914],
        "w": [0.5, 0.5, 0.5, 0.5, 0.5, 0.1, 0.5, 0.5, 0.5],
        "count": 7
    },
    "stone": {
        "x": [0.673, 0.265],
        "w": [0.5, 0.5],
        "count": 2
    },
    "marmalade": {
        "x": [1.0, 0.893],
        "w": [0.5, 0.5],
        "count": 2
    },
    "lemon": {
        "x": [0.235, 0.324, 0.021],
        "w": [0.6, 0.6, 0.6],
        "count": 3
    },
    "pear": {
        "x": [0.64, 1.0, 0.382],
        "w": [0.5, 0.5, 0.5],
        "count": 3
    },
    "citrus": {
        "x": [0.821, 0.773, 0.147, 0.714],
        "w": [0.5, 0.5, 0.5, 0.5],
        "count": 4
    },
    "melon": {
        "x": [0.16, 0.0],
        "w": [0.5, 0.5],
        "count": 2
    },
    "petrol": {
        "x": [0.357, 0.444, 0.417],
        "w": [0.5, 0.5, 0.5],
        "count": 3
    },
    "floral": {
        "x": [0.692, 0.091, 0.0],
        "w": [0.5, 0.5, 0.5],
        "count": 3
    },
    "grapefruit": {
        "x": [0.667, 0.571],
        "w": [0.36, 0.6],
        "count": 2
    }
}