{
    "honey": {
        "x": [0.822, 0.435, 1.0, 0.4, 0.4, 0.562, 0.199, 0.865, 0.0, 0.333, 0.6, 0.5, 0.438, 0.125, 0.285, 0.781, 0.518, 0.0],
        "w": [0.5, 0.1, 0.5, 0.5, 0.5, 0.5, 0.5, 0.1, 0.5, 0.5, 0.5, 0.15, 0.5, 0.5, 0.5, 0.5, 0.1, 0.5],
        "count": 16
    },
    "tropical": {
        "x": [0.867, 0.863, 0.296, 0.692, 0.21, 0.613, 0.125, 0.7, 0.511],
        "w": [0.5, 0.5, 0.5, 0.5, 0.5, 0.5, 0.5, 0.5, 0.5],
        "count": 8
    },
    "mineral": {
        "x": [0.778, 0.667, 0.167, 0.75, 0.429, 0.4, 0.905, 0.0, 0.944, 0.95, 0.0, 0.983, 0.261, 0.632, 0.0, 1.0, 0.355, 0.667, 0.0, 0.367, 0.35, 0.312, 1.0, 0.446, 0.333, 0.444],
        "w": [0.5, 0.5, 0.5, 0.5, 0.5, 0.5, 0.5, 0.5, 0.5, 0.5, 0.5, 0.5, 0.5, 0.5, 0.5, 0.5, 0.5, 0.5, 0.5, 0.5, 0.5, 0.5, 0.5, 0.1, 0.5, 0.5],
        "count": 25
    },
    "lemon": {
        "x": [0.087, 0.333, 0.233, 0.562, 0.619, 0.75, 0.028, 0.091, 0.083, 0.0, 0.34, 0.8, 1.0, 1.0, 0.02, 1.0, 0.629, 0.628, 0.097, 0.282, 0.593, 0.25, 0.091],
        "w": [0.75, 0.75, 0.75, 0.75, 0.75, 0.75, 0.45, 0.75, 0.75, 0.75, 0.75, 0.75, 0.75, 0.75, 0.75, 0.75, 0.75, 0.75, 0.75, 0.75, 0.75, 0.75, 0.75],
        "count": 22
    },
    "peach": {
        "x": [0.0, 0.714, 0.688, 1.0, 0.275, 0.771, 0.2, 0.707, 0.25, 0.25, 0.1, 0.235, 0.574, 0.32, 0.367],
        "w": [0.5, 0.5, 0.5, 0.5, 0.5, 0.5, 0.5, 0.5, 0.5, 0.5, 0.2, 0.5, 0.5, 0.5, 0.5],
        "count": 15
    },
    "ripe": {
        "x": [0.149, 0.357, 0.243, 0.715, 0.185, 0.712, 0.833, 0.531, 0.641, 0.719, 0.207],
        "w": [0.5, 0.5, 0.5, 0.5, 0.5, 0.5, 0.5, 0.5, 0.5, 0.5, 0.5],
        "count": 8
    },
    "apple": {
        "x": [0.234, 0.784, 0.0, 0.273, 0.751, 0.444, 0.5, 0.603, 0.263, 0.5, 0.419, 0.833, 0.5, 0.547, 0.25, 0.554, 0.5, 0.25, 0.0, 0.273, 0.0, 0.1],
        "w": [0.5, 0.5, 0.5, 0.5, 0.5, 0.5, 0.5, 0.5, 0.5, 0.5, 0.5, 0.5, 0.5, 0.5, 0.5, 0.5, 0.5, 0.5, 0.5, 0.5, 0.5, 0.5],
        "count": 20
    },
    "citrus": {
        "x": [0.106, 0.812, 1.0, 0.431, 0.2, 0.259, 0.735, 0.625, 0.702, 0.713, 0.75, 0.269, 0.375, 0.222, 0.638, 0.515, 0.717, 1.0, 0.6],
        "w": [0.5, 0.5, 0.5, 0.5, 0.5, 0.5, 0.5, 0.5, 0.5, 0.5, 0.5, 0.5, 0.5, 0.5, 0.5, 0.5, 0.5, 0.5, 0.5],
        "count": 18
    },
    "pineapple": {
        "x": [0.277, 0.95, 0.243, 0.433, 0.377, 0.846],
        "w": [0.56, 0.56, 0.56, 0.56, 0.56, 0.56],
        "count": 5
    },
    "floral": {
        "x": [0.367, 0.844, 0.333, 0.526, 0.5, 0.548, 0.227, 0.482, 0.667],
        "w": [0.5, 0.5, 0.5, 0.5, 0.5, 0.5, 0.5, 0.5, 0.5],
        "count": 8
    },
    "lime": {
        "x": [0.625, 0.215, 0.767, 0.426, 0.9, 0.161, 0.3, 1.0, 1.0, 0.0],
        "w": [0.75, 0.75, 0.75, 0.75, 0.75, 0.75, 0.75, 0.75, 0.75, 0.75],
        "count": 10
    },
    "grapefruit": {
        "x": [0.3, 0.226, 0.681, 0.444],
        "w": [0.75, 0.75, 0.75, 0.75],
        "count": 4
    },
    "beeswax": {
        "x": [0.0, 0.808],
        "w": [0.5, 0.5],
        "count": 2
    },
    "stone": {
        "x": [0.476, 0.413, 0.364, 0.776, 0.917, 0.724, 0.29, 0.4, 0.25, 0.533, 0.238],
        "w": [0.5, 0.5, 0.5, 0.5, 0.1, 0.5, 0.5, 0.5, 0.5, 0.5, 0.5],
        "count": 11
    },
    "petrol": {
        "x": [0.119, 0.247, 0.125, 0.0, 0.331, 0.917, 0.5, 0.5, 1.0, 0.333],
        "w": [0.5, 0.5, 0.5, 0.5, 0.1, 0.15, 0.5, 0.5, 0.5, 0.5],
        "count": 10
    },
    "ginger": {
        "x": [0.904, 0.301],
        "w": [0.5, 0.5],
        "count": 2
    },
    "apricot": {
        "x": [0.0, 0.486, 0.3, 0.625, 0.25, 0.259, 0.438, 0.0, 1.0],
        "w": [0.5, 0.5, 0.5, 0.5, 0.5, 0.5, 0.5, 0.5, 0.5],
        "count": 8
    },
    "fruity": {
        "x": [0.0, 0.182, 0.5, 1.0],
        "w": [0.5, 0.5, 0.5, 0.5],
        "count": 4
    },
    "honeysuckle": {
        "x": [0.357, 0.541],
        "w": [0.56, 0.56],
        "count": 2
    },
    "pear": {
        "x": [0.182, 1.0, 0.484, 0.181, 0.578, 0.154],
        "w": [0.5, 0.5, 0.5, 0.5, 0.5, 0.5],
        "count": 5
    },
    "black tea": {
        "x": [0.571, 1.0],
        "w": [0.5, 0.5],
        "count": 2
    },
    "orange peel": {
        "x": [0.929, 0.372, 0.731],
        "w": [0.75, 0.75, 0.75],
        "count": 3
    },
    "flint": {
        "x": [0.404, 0.866, 0.388],
        "w": [0.5, 0.5, 0.5],
        "count": 3
    },
    "green apple": {
        "x": [0.647, 0.093, 0.208, 0.625, 0.146, 0.329, 0.522, 0.562],
        "w": [0.5, 0.5, 0.5, 0.5, 0.5, 0.5, 0.5, 0.5],
        "count": 8
    }
}