{
    "cherry": {
        "x": [0.553, 0.238, 0.758, 0.23, 0.361, 0.611, 0.75, 0.857],
        "w": [0.5, 0.5, 0.5, 0.5, 0.5, 0.5, 0.5, 0.5],
        "count": 5
    },
    "rose": {
        "x": [0.132, 0.331],
        "w": [0.5, 0.5],
        "count": 2
    },
    "toast": {
        "x": [0.658, 0.611],
        "w": [0.5, 0.1],
        "count": 2
    },
    "strawberry": {
        "x": [0.285, 0.262],
        "w": [0.5, 0.5],
        "count": 2
    },
    "chocolate": {
        "x": [0.377, 0.821],
        "w": [0.5, 0.5],
        "count": 2
    },
    "vanilla": {
        "x": [0.515, 0.229],
        "w": [0.5, 0.5],
        "count": 2
    },
    "raspberry": {
        "x": [0.192, 0.393, 0.293],
        "w": [0.5, 0.5, 0.5],
        "count": 3
    },
    "violet": {
        "x": [0.208, 0.19],
        "w": [0.5, 0.5],
        "count": 2
    },
    "plum": {
        "x": [0.311, 0.833, 0.389, 0.0],
        "w": [0.5, 0.5, 0.5, 0.5],
        "count": 3
    }
}