{
    "forest floor": {
        "x": [0.455, 0.238, 0.706],
        "w": [0.51, 0.51, 0.51],
        "count": 3
    },
    "red fruit": {
        "x": [0.065, 0.019, 0.218],
        "w": [0.5, 0.5, 0.5],
        "count": 3
    },
    "mushroom": {
        "x": [0.494, 0.519, 0.143, 0.882, 0.237, 0.32],
        "w": [0.51, 0.51, 0.51, 0.51, 0.51, 0.51],
        "count": 5
    },
    "lavender": {
        "x": [0.325, 0.542],
        "w": [0.5, 0.5],
        "count": 2
    },
    "cherry": {
        "x": [0.104, 0.238, 0.093, 0.333, 0.333, 0.176, 0.471, 0.184],
        "w": [0.64, 0.64, 0.64, 0.64, 0.64, 0.64, 0.64, 0.64],
        "count": 6
    },
    "raspberry": {
        "x": [0.143, 0.169, 0.13, 0.0, 0.105],
        "w": [0.64, 0.64, 0.64, 0.64, 0.64],
        "count": 5
    },
    "earthy": {
        "x": [0.463, 0.208],
        "w": [0.15, 0.5],
        "count": 2
    }
}