{
    "anise": {
        "x": [0.774, 0.593],
        "w": [0.5, 0.5],
        "count": 2
    },
    "cherry": {
        "x": [0.276, 0.857, 0.467, 0.0, 0.893, 0.049, 0.28, 0.25, 0.0, 0.841, 1.0, 0.4, 1.0, 0.75, 0.917, 1.0, 0.778, 0.0, 0.0, 0.0],
        "w": [0.5, 0.5, 0.5, 0.5, 0.5, 0.5, 0.5, 0.5, 0.5, 0.5, 0.5, 0.5, 0.5, 0.5, 0.5, 0.5, 0.5, 0.5, 0.5, 0.5],
        "count": 19
    },
    "oak": {
        "x": [0.186, 1.0, 0.818, 0.267, 1.0, 0.914, 1.0, 0.8, 0.795, 0.0, 0.0, 0.875, 0.792, 0.667, 0.75, 1.0, 0.5, 0.667],
        "w": [0.63, 0.63, 0.63, 0.63, 0.63, 0.63, 0.63, 0.63, 0.63, 0.63, 0.63, 0.63, 0.63, 0.63, 0.63, 0.63, 0.63, 0.63],
        "count": 18
    },
    "vanilla": {
        "x": [0.643, 0.936, 0.28, 0.1, 1.0, 1.0, 0.0, 0.5],
        "w": [0.5, 0.5, 0.1, 0.5, 0.5, 0.5, 0.5, 0.5],
        "count": 8
    },
    "blackberry": {
        "x": [0.429, 0.286, 0.2, 0.833, 0.444, 0.889, 0.0, 1.0, 0.333],
        "w": [0.5, 0.5, 0.5, 0.5, 0.5, 0.5, 0.5, 0.5, 0.5],
        "count": 9
    },
    "red fruit": {
        "x": [0.25, 0.071],
        "w": [0.5, 0.5],
        "count": 2
    },
    "pepper": {
        "x": [1.0, 0.304, 0.957, 0.875, 0.11, 0.886, 0.958, 0.556, 0.25],
        "w": [0.5, 0.15, 0.5, 0.2, 0.5, 0.5, 0.5, 0.5, 0.5],
        "count": 9
    },
    "earthy": {
        "x": [0.0, 1.0, 0.062, 0.25, 0.5, 0.889, 1.0],
        "w": [0.5, 0.5, 0.5, 0.5, 0.5, 0.5, 0.5],
        "count": 7
    },
    "tobacco": {
        "x": [0.979, 0.085, 0.375, 0.778, 1.0],
        "w": [0.5, 0.5, 0.5, 0.5, 0.5],
        "count": 5
    },
    "plum": {
        "x": [0.317, 1.0, 0.5],
        "w": [0.5, 0.5, 0.5],
        "count": 3
    },
    "leather": {
        "x": [0.0, 0.5],
        "w": [0.63, 0.63],
        "count": 2
    },
    "fruity": {
        "x": [0.944, 1.0, 0.4],
        "w": [0.5, 0.5, 0.5],
        "count": 3
    },
    "strawberry": {
        "x": [0.8, 1.0],
        "w": [0.5, 0.5],
        "count": 2
    }
}