{
    "oak": {
        "x": [0.077, 0.692, 0.306],
        "w": [0.5, 0.5, 0.5],
        "count": 3
    },
    "coffee": {
        "x": [0.229, 0.287],
        "w": [0.5, 0.5],
        "count": 2
    },
    "cherry": {
        "x": [0.018, 0.103, 0.641, 0.455, 0.383, 0.561, 0.339],
        "w": [0.5, 0.5, 0.5, 0.5, 0.5, 0.5, 0.5],
        "count": 5
    },
    "leather": {
        "x": [0.263, 0.4],
        "w": [0.1, 0.5],
        "count": 2
    },
    "mushroom": {
        "x": [0.818, 0.285],
        "w": [0.5, 0.5],
        "count": 2
    },
    "raspberry": {
        "x": [0.286, 0.138, 0.125, 0.758, 0.354, 0.673],
        "w": [0.5, 0.5, 0.5, 0.5, 0.5, 0.15],
        "count": 4
    },
    "chocolate": {
        "x": [0.596, 0.25, 0.667, 0.411],
        "w": [0.5, 0.5, 0.5, 0.5],
        "count": 3
    }
}