{
    "violet": {
        "x": [0.053, 0.548, 0.302, 1.0, 0.42, 0.0],
        "w": [0.53, 0.53, 0.53, 0.53, 0.53, 0.53],
        "count": 6
    },
    "orange peel": {
        "x": [0.263, 0.781],
        "w": [0.5, 0.1],
        "count": 2
    },
    "eucalyptus": {
        "x": [0.55, 0.571, 0.952, 0.684, 0.318],
        "w": [0.5, 0.5, 0.5, 0.5, 0.5],
        "count": 5
    },
    "raspberry": {
        "x": [1.0, 0.897, 0.429, 0.644, 0.883, 0.269],
        "w": [0.5, 0.5, 0.5, 0.5, 0.5, 0.5],
        "count": 5
    },
    "leather": {
        "x": [0.75, 1.0, 0.41, 0.656, 0.04, 0.952, 0.45, 0.0, 0.0, 0.167, 0.606, 0.667, 0.229, 0.571, 0.341, 0.352, 0.714, 0.282, 0.857, 0.213],
        "w": [0.5, 0.5, 0.2, 0.5, 0.5, 0.5, 0.5, 0.5, 0.5, 0.5, 0.5, 0.5, 0.5, 0.5, 0.5, 0.5, 0.5, 0.5, 0.5, 0.5],
        "count": 19
    },
    "earthy": {
        "x": [0.875, 0.462, 0.5],
        "w": [0.5, 0.5, 0.5],
        "count": 3
    },
    "cherry": {
        "x": [0.625, 0.316, 0.323, 0.75, 0.2, 0.597, 0.28, 0.74, 0.914, 0.283, 0.333, 0.647, 0.25, 0.946, 0.114, 0.182, 0.622, 0.168, 0.24, 1.0, 0.0, 0.353, 0.266, 0.556, 0.143, 0.814, 0.143, 1.0, 0.239, 0.624, 0.027, 1.0, 0.12, 0.231, 0.325, 0.267],
        "w": [0.5, 0.5, 0.5, 0.5, 0.5, 0.5, 0.5, 0.5, 0.5, 0.15, 0.5, 0.5, 0.5, 0.5, 0.5, 0.5, 0.5, 0.5, 0.5, 0.5, 0.5, 0.5, 0.5, 0.5, 0.5, 0.5, 0.5, 0.5, 0.5, 0.5, 0.5, 0.5, 0.5, 0.5, 0.5, 0.5],
        "count": 31
    },
    "oak": {
        "x": [0.5, 0.225, 0.56, 1.0, 0.25, 0.895, 0.7, 0.5, 0.905, 0.0, 0.0],
        "w": [0.5, 0.5, 0.5, 0.5, 0.5, 0.5, 0.15, 0.5, 0.5, 0.5, 0.5],
        "count": 11
    },
    "forest floor": {
        "x": [0.0, 0.2, 0.054],
        "w": [0.5, 0.5, 0.5],
        "count": 3
    },
    "prune": {
        "x": [0.75, 0.467, 0.068],
        "w": [0.5, 0.5, 0.5],
        "count": 3
    },
    "plum": {
        "x": [0.025, 0.617, 0.651, 0.2],
        "w": [0.5, 0.5, 0.5, 0.5],
        "count": 4
    },
    "ripe": {
        "x": [0.0, 0.45, 0.625, 0.172, 0.0, 0.878, 0.276],
        "w": [0.5, 0.5, 0.5, 0.5, 0.5, 0.5, 0.5],
        "count": 5
    },
    "chocolate": {
        "x": [0.575, 0.75, 0.12, 0.762, 0.0, 0.882, 0.333, 0.335, 0.8, 0.953],
        "w": [0.5, 0.5, 0.5, 0.5, 0.5, 0.5, 0.5, 0.5, 0.5, 0.5],
        "count": 10
    },
    "strawberry": {
        "x": [0.484, 0.294],
        "w": [0.5, 0.5],
        "count": 2
    },
    "tar": {
        "x": [0.387, 0.5, 0.0, 0.957, 0.4, 0.25, 0.333, 0.579, 0.667, 0.213, 0.667, 0.714, 0.732, 0.44, 0.051, 0.133, 0.269],
        "w": [0.5, 0.5, 0.5, 0.5, 0.5, 0.5, 0.5, 0.5, 0.5, 0.5, 0.5, 0.5, 0.5, 0.5, 0.5, 0.5, 0.5],
        "count": 17
    },
    "tobacco": {
        "x": [0.613, 0.4, 0.702, 0.765, 0.744, 0.095, 0.5, 0.433],
        "w": [0.5, 0.5, 0.5, 0.5, 0.5, 0.5, 0.5, 0.5],
        "count": 8
    },
    "truffle": {
        "x": [0.5, 0.637, 0.486, 0.25, 0.5, 0.759],
        "w": [0.5, 0.5, 0.5, 0.5, 0.5, 0.5],
        "count": 6
    },
    "rose": {
        "x": [0.3, 0.128, 0.389, 0.18, 0.964, 0.258, 0.0, 0.156, 0.368, 0.071, 0.8, 0.5, 0.857, 0.705, 0.103, 0.156, 0.2],
        "w": [0.53, 0.53, 0.53, 0.53, 0.53, 0.53, 0.53, 0.53, 0.53, 0.53, 0.53, 0.53, 0.53, 0.53, 0.53, 0.53, 0.53],
        "count": 17
    },
    "mint": {
        "x": [0.179, 0.32, 0.667, 0.96, 0.75, 0.762, 0.9, 0.949, 0.2],
        "w": [0.5, 0.5, 0.5, 0.5, 0.5, 0.5, 0.5, 0.5, 0.5],
        "count": 9
    },
    "liquorice": {
        "x": [0.686, 0.522, 0.836, 0.957, 0.857, 0.722, 0.333, 0.409, 0.237, 0.286, 0.284, 0.52, 0.188, 0.466],
        "w": [0.2, 0.5, 0.5, 0.5, 0.5, 0.5, 0.5, 0.5, 0.5, 0.5, 0.5, 0.5, 0.5, 0.5],
        "count": 13
    },
    "coffee": {
        "x": [0.08, 0.78, 1.0, 0.867, 0.429, 0.477, 0.969, 0.359, 0.0, 0.522],
        "w": [0.5, 0.5, 0.5, 0.5, 0.5, 0.5, 0.5, 0.15, 0.5, 0.5],
        "count": 9
    },
    "floral": {
        "x": [0.828, 0.022, 0.22, 0.629, 0.6, 0.19],
        "w": [0.5, 0.5, 0.5, 0.5, 0.5, 0.5],
        "count": 6
    },
    "red fruit": {
        "x": [0.188, 0.667, 0.321, 0.128, 0.381],
        "w": [0.5, 0.5, 0.5, 0.5, 0.5],
        "count": 5
    },
    "cedar": {
        "x": [0.098, 0.986],
        "w": [0.5, 0.5],
        "count": 2
    },
    "mineral": {
        "x": [0.94, 0.971, 1.0],
        "w": [0.5, 0.5, 0.5],
        "count": 3
    },
    "black tea": {
        "x": [0.154, 0.4, 0.4],
        "w": [0.5, 0.5, 0.5],
        "count": 3
    }
}