{
    "fruity": {
        "x": [0.463, 0.187],
        "w": [0.5, 0.5],
        "count": 2
    },
    "green apple": {
        "x": [0.417, 0.0, 0.316, 0.8],
        "w": [0.5, 0.5, 0.5, 0.1],
        "count": 4
    },
    "mineral": {
        "x": [0.75, 0.725, 0.25, 1.0],
        "w": [0.5, 0.5, 0.5, 0.5],
        "count": 4
    },
    "citrus": {
        "x": [0.667, 0.261, 0.25, 0.333, 0.0, 0.0, 0.4, 0.643, 0.0, 0.147, 0.6],
        "w": [0.5, 0.5, 0.5, 0.5, 0.5, 0.5, 0.5, 0.5, 0.5, 0.5, 0.5],
        "count": 11
    },
    "lemon": {
        "x": [0.583, 0.088, 0.806, 0.211, 0.137, 0.173, 0.462, 0.275, 0.229, 0.8, 0.297, 0.574, 0.5],
        "w": [0.75, 0.75, 0.75, 0.75, 0.75, 0.75, 0.75, 0.75, 0.75, 0.75, 0.22, 0.75, 0.75],
        "count": 12
    },
    "plum": {
        "x": [0.235, 0.188, 0.75],
        "w": [0.5, 0.5, 0.5],
        "count": 3
    },
    "lime": {
        "x": [0.147, 0.333, 0.667],
        "w": [0.75, 0.75, 0.75],
        "count": 2
    },
    "yeast": {
        "x": [0.294, 0.474, 0.196, 0.6, 0.209],
        "w": [0.5, 0.5, 0.5, 0.5, 0.5],
        "count": 5
    },
    "grapefruit": {
        "x": [0.471, 0.55, 1.0],
        "w": [0.75, 0.75, 0.75],
        "count": 3
    },
    "oak": {
        "x": [0.263, 0.375, 0.139, 0.722, 0.078],
        "w": [0.5, 0.5, 0.5, 0.5, 0.5],
        "count": 4
    },
    "chalk": {
        "x": [0.229, 0.833, 0.2],
        "w": [0.5, 0.5, 0.5],
        "count": 3
    },
    "toast": {
        "x": [0.486, 0.941],
        "w": [0.5, 0.5],
        "count": 2
    },
    "apple": {
        "x": [0.376, 0.421, 0.077, 0.308, 0.486, 0.225, 0.708],
        "w": [0.5, 0.5, 0.5, 0.5, 0.5, 0.5, 0.5],
        "count": 5
    },
    "earthy": {
        "x": [0.486, 0.833],
        "w": [0.5, 0.5],
        "count": 2
    },
    "peach": {
        "x": [0.316, 0.2],
        "w": [0.5, 0.5],
        "count": 2
    },
    "floral": {
        "x": [0.353, 0.294],
        "w": [0.5, 0.5],
        "count": 2
    },
    "bread": {
        "x": [0.3, 0.186, 0.149],
        "w": [0.5, 0.5, 0.5],
        "count": 3
    }
}