{
    "oak": {
        "x": [0.5, 0.906, 0.0, 0.0, 0.471, 0.0, 0.571, 0.0, 1.0, 0.792, 0.167, 0.75],
        "w": [0.5, 0.5, 0.5, 0.5, 0.5, 0.5, 0.5, 0.5, 0.5, 0.5, 0.5, 0.5],
        "count": 12
    },
    "vanilla": {
        "x": [1.0, 0.357, 0.969, 0.714, 0.667, 0.714, 0.8, 0.704, 0.85],
        "w": [0.5, 0.5, 0.5, 0.1, 0.5, 0.5, 0.5, 0.5, 0.1],
        "count": 9
    },
    "leather": {
        "x": [0.643, 0.367, 1.0, 0.167, 1.0, 0.0],
        "w": [0.5, 0.5, 0.5, 0.5, 0.5, 0.5],
        "count": 6
    },
    "cherry": {
        "x": [0.614, 0.475, 0.236, 0.333, 0.571, 0.273, 0.147, 0.857, 1.0, 0.4, 0.25, 0.364, 0.775],
        "w": [0.5, 0.5, 0.5, 0.5, 0.5, 0.5, 0.5, 0.5, 0.5, 0.5, 0.5, 0.5, 0.5],
        "count": 13
    },
    "chocolate": {
        "x": [0.24, 0.286, 0.619],
        "w": [0.5, 0.5, 0.5],
        "count": 3
    },
    "plum": {
        "x": [0.363, 0.315, 0.155, 0.455],
        "w": [0.5, 0.5, 0.5, 0.5],
        "count": 4
    },
    "fruity": {
        "x": [0.138, 0.0, 0.0],
        "w": [0.5, 0.5, 0.5],
        "count": 3
    },
    "clove": {
        "x": [0.625, 0.345],
        "w": [0.5, 0.5],
        "count": 2
    },
    "tobacco": {
        "x": [0.55, 1.0],
        "w": [0.5, 0.5],
        "count": 2
    },
    "blackberry": {
        "x": [0.333, 0.625, 0.75, 0.788],
        "w": [0.5, 0.5, 0.1, 0.5],
        "count": 4
    }
}