{
    "tobacco": {
        "x": [0.571, 0.5, 0.5, 0.143, 0.429],
        "w": [0.5, 0.5, 0.5, 0.5, 0.5],
        "count": 5
    },
    "earthy": {
        "x": [0.357, 0.0, 0.0],
        "w": [0.5, 0.5, 0.5],
        "count": 3
    },
    "pepper": {
        "x": [1.0, 0.8],
        "w": [0.5, 0.5],
        "count": 2
    },
    "plum": {
        "x": [0.5, 0.591, 0.9, 0.333, 0.714, 0.525],
        "w": [0.5, 0.5, 0.5, 0.5, 0.5, 0.15],
        "count": 6
    },
    "oak": {
        "x": [1.0, 1.0, 0.0, 0.375],
        "w": [0.57, 0.57, 0.57, 0.57],
        "count": 4
    },
    "leather": {
        "x": [0.65, 1.0, 0.571, 1.0],
        "w": [0.57, 0.57, 0.57, 0.57],
        "count": 4
    },
    "cherry": {
        "x": [1.0, 0.286],
        "w": [0.5, 0.5],
        "count": 2
    },
    "chocolate": {
        "x": [0.0, 0.308],
        "w": [0.5, 0.5],
        "count": 2
    }
}