{
    "cherry": {
        "x": [0.824, 0.257, 0.367, 0.4, 0.444, 0.562, 0.0, 0.429, 0.222, 0.467, 0.662, 0.113, 0.0, 0.027, 0.538, 0.0, 0.556, 0.833, 1.0, 0.0, 0.8, 0.148, 0.152, 0.204, 0.895, 0.195, 0.317, 0.0, 0.9, 0.024, 0.176, 0.793, 0.417, 0.28, 0.095, 1.0, 0.294, 0.538, 0.567, 0.429, 0.636, 0.773, 0.7, 0.575, 0.159, 0.183, 0.67, 0.136, 0.173, 0.917, 0.167, 0.274, 0.0, 0.0],
        "w": [0.62, 0.62, 0.62, 0.62, 0.62, 0.62, 0.62, 0.62, 0.62, 0.62, 0.62, 0.62, 0.62, 0.62, 0.62, 0.62, 0.62, 0.62, 0.62, 0.62, 0.62, 0.62, 0.62, 0.62, 0.62, 0.62, 0.62, 0.62, 0.62, 0.62, 0.62, 0.62, 0.62, 0.62, 0.62, 0.62, 0.62, 0.62, 0.62, 0.62, 0.62, 0.62, 0.62, 0.62, 0.62, 0.62, 0.62, 0.62, 0.62, 0.62, 0.62, 0.62, 0.62, 0.62],
        "count": 45
    },
    "oak": {
        "x": [0.353, 0.7, 0.762, 0.533, 0.143, 0.222, 0.0, 0.55, 0.236, 0.2, 0.0, 1.0, 0.381, 0.412, 1.0, 0.367, 0.817, 0.945, 0.368],
        "w": [0.75, 0.75, 0.75, 0.75, 0.75, 0.75, 0.75, 0.75, 0.15, 0.75, 0.75, 0.75, 0.75, 0.75, 0.75, 0.75, 0.75, 0.75, 0.75],
        "count": 17
    },
    "red fruit": {
        "x": [0.159, 0.627, 0.933, 0.136, 0.0, 0.275],
        "w": [0.5, 0.5, 0.5, 0.5, 0.5, 0.5],
        "count": 5
    },
    "earthy": {
        "x": [0.786, 0.167, 0.0, 0.0, 0.325, 0.8, 1.0, 0.143, 0.0, 0.067, 0.969, 0.1, 0.471, 0.826, 0.0, 0.917, 0.46, 0.0, 0.706, 0.294, 0.721, 0.5],
        "w": [0.5, 0.5, 0.5, 0.5, 0.5, 0.5, 0.5, 0.5, 0.5, 0.5, 0.5, 0.5, 0.5, 0.5, 0.5, 0.5, 0.5, 0.5, 0.5, 0.5, 0.5, 0.5],
        "count": 22
    },
    "raspberry": {
        "x": [0.217, 0.3, 0.267, 0.4, 0.081, 0.5, 0.04, 0.4, 0.238, 0.35, 0.268, 0.441, 0.2, 0.0, 0.875, 0.534, 0.045, 0.233, 0.615, 0.197, 0.162, 1.0],
        "w": [0.62, 0.62, 0.62, 0.62, 0.62, 0.62, 0.62, 0.62, 0.62, 0.62, 0.62, 0.62, 0.62, 0.62, 0.62, 0.62, 0.62, 0.62, 0.62, 0.62, 0.62, 0.62],
        "count": 20
    },
    "ripe": {
        "x": [0.3, 0.114],
        "w": [0.5, 0.5],
        "count": 2
    },
    "cedar": {
        "x": [0.769, 0.444, 0.925],
        "w": [0.75, 0.75, 0.15],
        "count": 3
    },
    "strawberry": {
        "x": [0.2, 0.6, 0.81, 1.0, 0.286, 1.0, 0.25, 0.333, 0.12, 0.379, 0.4, 0.7, 0.19, 0.0, 0.5, 0.0, 0.167],
        "w": [0.62, 0.62, 0.62, 0.62, 0.62, 0.62, 0.62, 0.62, 0.62, 0.62, 0.62, 0.62, 0.62, 0.62, 0.62, 0.62, 0.62],
        "count": 15
    },
    "blackberry": {
        "x": [0.875, 0.385, 1.0, 0.286],
        "w": [0.12, 0.62, 0.62, 0.62],
        "count": 4
    },
    "forest floor": {
        "x": [0.571, 0.342, 0.985, 0.5, 0.331, 0.992],
        "w": [0.75, 0.75, 0.75, 0.75, 0.75, 0.75],
        "count": 4
    },
    "chocolate": {
        "x": [1.0, 0.685],
        "w": [0.5, 0.5],
        "count": 2
    },
    "vanilla": {
        "x": [0.69, 0.283, 0.672, 0.725],
        "w": [0.5, 0.5, 0.5, 0.5],
        "count": 4
    },
    "fruity": {
        "x": [0.7, 1.0, 0.75, 0.0, 0.111, 0.393, 0.481, 0.975],
        "w": [0.5, 0.5, 0.5, 0.5, 0.5, 0.5, 0.5, 0.5],
        "count": 8
    },
    "leather": {
        "x": [0.438, 0.667],
        "w": [0.75, 0.75],
        "count": 2
    },
    "tomato": {
        "x": [0.58, 0.752],
        "w": [0.75, 0.75],
        "count": 2
    },
    "mushroom": {
        "x": [0.34, 0.72, 0.394, 0.955, 0.5, 0.071, 0.286, 0.333, 0.4, 0.428, 0.609, 0.333],
        "w": [0.75, 0.75, 0.75, 0.75, 0.75, 0.75, 0.75, 0.75, 0.75, 0.75, 0.75, 0.75],
        "count": 10
    },
    "plum": {
        "x": [1.0, 0.024, 0.071],
        "w": [0.5, 0.5, 0.5],
        "count": 3
    },
    "mineral": {
        "x": [0.2, 0.87, 0.034],
        "w": [0.75, 0.75, 0.75],
        "count": 3
    },
    "perfume": {
        "x": [0.857, 0.037],
        "w": [0.5, 0.5],
        "count": 2
    },
    "rose": {
        "x": [0.294, 0.0],
        "w": [0.5, 0.5],
        "count": 2
    },
    "tobacco": {
        "x": [0.571, 1.0],
        "w": [0.5, 0.5],
        "count": 2
    }
}