{
    "oak": {
        "x": [0.232, 0.6, 0.167, 0.857, 0.286, 0.077, 0.7, 1.0, 0.6, 0.0, 0.861, 0.359, 1.0],
        "w": [0.5, 0.5, 0.5, 0.5, 0.5, 0.5, 0.5, 0.5, 0.5, 0.5, 0.15, 0.5, 0.5],
        "count": 13
    },
    "citrus": {
        "x": [0.341, 1.0, 1.0, 0.75, 0.632],
        "w": [0.5, 0.5, 0.5, 0.5, 0.5],
        "count": 5
    },
    "honey": {
        "x": [0.298, 0.2, 0.857, 0.6, 0.333, 0.5, 0.222],
        "w": [0.5, 0.5, 0.5, 0.5, 0.5, 0.5, 0.5],
        "count": 7
    },
    "apricot": {
        "x": [0.32, 0.8, 0.333, 0.417, 0.778],
        "w": [0.5, 0.5, 0.5, 0.5, 0.5],
        "count": 5
    },
    "pear": {
        "x": [0.936, 0.833, 0.639, 0.222, 0.75],
        "w": [0.5, 0.5, 0.5, 0.5, 0.5],
        "count": 5
    },
    "lemon": {
        "x": [0.113, 0.476],
        "w": [0.57, 0.57],
        "count": 2
    },
    "green apple": {
        "x": [0.254, 0.667, 0.286, 0.19, 0.571, 0.0, 0.167, 0.0, 0.556, 0.933],
        "w": [0.5, 0.5, 0.5, 0.5, 0.5, 0.5, 0.5, 0.5, 0.5, 0.5],
        "count": 10
    },
    "apple": {
        "x": [0.4, 0.5, 0.8, 0.5, 0.192, 0.5, 0.25],
        "w": [0.5, 0.5, 0.5, 0.5, 0.5, 0.5, 0.5],
        "count": 7
    },
    "butter": {
        "x": [0.0, 0.0, 0.429, 1.0, 0.5, 0.75, 0.938, 1.0, 0.083, 0.131, 0.0, 0.8, 1.0, 1.0],
        "w": [0.5, 0.5, 0.5, 0.5, 0.5, 0.5, 0.5, 0.5, 0.5, 0.5, 0.5, 0.5, 0.5, 0.5],
        "count": 14
    },
    "stone": {
        "x": [0.444, 0.722],
        "w": [0.5, 0.5],
        "count": 2
    },
    "mineral": {
        "x": [0.0, 0.857, 1.0, 0.583, 0.161, 0.789, 1.0],
        "w": [0.5, 0.5, 0.5, 0.5, 0.5, 0.5, 0.5],
        "count": 7
    },
    "vanilla": {
        "x": [0.571, 0.231, 0.667, 0.179, 0.0],
        "w": [0.5, 0.5, 0.5, 0.5, 0.5],
        "count": 5
    },
    "cream": {
        "x": [0.714, 0.667, 0.917, 0.206],
        "w": [0.5, 0.1, 0.5, 0.5],
        "count": 4
    },
    "fruity": {
        "x": [0.143, 0.316, 0.6],
        "w": [0.5, 0.5, 0.5],
        "count": 3
    },
    "cherry": {
        "x": [0.0, 0.333],
        "w": [0.5, 0.15],
        "count": 2
    }
}