{
    "violet": {
        "x": [0.071, 0.717, 0.089, 0.238, 0.75, 0.5, 0.69, 0.469, 0.105],
        "w": [0.51, 0.51, 0.51, 0.51, 0.51, 0.51, 0.51, 0.51, 0.51],
        "count": 9
    },
    "cherry": {
        "x": [0.179, 0.857, 0.846, 0.135, 0.31, 0.88, 0.143, 0.696, 0.5, 0.544, 0.864, 0.188, 1.0, 0.264, 0.178, 0.222, 0.667, 0.308, 0.12, 0.345, 0.25, 0.727, 0.267],
        "w": [0.75, 0.75, 0.75, 0.75, 0.75, 0.75, 0.75, 0.75, 0.75, 0.75, 0.75, 0.75, 0.75, 0.75, 0.75, 0.75, 0.75, 0.75, 0.75, 0.75, 0.75, 0.75, 0.75],
        "count": 18
    },
    "leather": {
        "x": [0.929, 0.144, 0.167, 0.82, 0.381, 0.192, 0.062, 0.167, 0.263, 0.833, 0.517, 0.125, 0.906, 0.925, 0.217],
        "w": [0.75, 0.75, 0.75, 0.75, 0.75, 0.75, 0.75, 0.75, 0.75, 0.75, 0.75, 0.75, 0.75, 0.75, 0.75],
        "count": 13
    },
    "smoke": {
        "x": [0.227, 0.232, 0.125, 0.688],
        "w": [0.5, 0.5, 0.5, 0.5],
        "count": 3
    },
    "mineral": {
        "x": [0.962, 0.357, 0.78, 0.97, 1.0, 0.985, 0.5, 0.0],
        "w": [0.75, 0.75, 0.75, 0.75, 0.75, 0.75, 0.75, 0.75],
        "count": 7
    },
    "floral": {
        "x": [0.136, 0.335, 0.714, 0.444, 0.614],
        "w": [0.5, 0.5, 0.5, 0.5, 0.5],
        "count": 5
    },
    "raspberry": {
        "x": [0.65, 0.169, 0.308, 0.773, 0.438, 0.0, 0.111, 0.267, 0.0, 0.04, 0.276, 0.405, 0.75, 0.0, 0.4],
        "w": [0.75, 0.75, 0.75, 0.75, 0.75, 0.75, 0.75, 0.75, 0.75, 0.75, 0.75, 0.75, 0.75, 0.75, 0.75],
        "count": 15
    },
    "bacon": {
        "x": [0.254, 0.496, 1.0],
        "w": [0.5, 0.5, 0.5],
        "count": 3
    },
    "tobacco": {
        "x": [0.612, 0.804, 0.846, 0.714],
        "w": [0.5, 0.5, 0.5, 0.5],
        "count": 4
    },
    "capsicum": {
        "x": [0.38, 0.817, 0.095, 0.423, 0.87, 0.495, 0.353, 0.917, 0.222, 0.511, 0.333, 0.4, 0.586, 0.125, 0.375, 0.226, 0.321, 0.655, 0.455],
        "w": [0.75, 0.75, 0.75, 0.75, 0.75, 0.75, 0.75, 0.75, 0.75, 0.75, 0.75, 0.75, 0.75, 0.75, 0.75, 0.75, 0.75, 0.75, 0.75],
        "count": 19
    },
    "red fruit": {
        "x": [0.244, 0.071, 0.238, 0.5, 0.059, 0.138, 0.68, 0.917, 0.044, 0.0, 0.0, 0.0, 0.136, 0.5, 0.708, 0.727],
        "w": [0.5, 0.5, 0.5, 0.5, 0.5, 0.5, 0.5, 0.5, 0.5, 0.5, 0.5, 0.5, 0.5, 0.5, 0.5, 0.5],
        "count": 15
    },
    "pepper": {
        "x": [0.457, 0.667, 1.0, 0.364, 0.7, 0.44, 1.0, 1.0, 1.0, 0.182],
        "w": [0.5, 0.5, 0.5, 0.5, 0.5, 0.5, 0.5, 0.5, 0.5, 0.5],
        "count": 10
    },
    "ripe": {
        "x": [0.224, 0.769, 0.848, 0.0, 0.656, 0.133],
        "w": [0.5, 0.5, 0.5, 0.5, 0.5, 0.5],
        "count": 6
    },
    "earthy": {
        "x": [0.535, 0.333, 0.74, 0.75, 0.756, 0.5, 0.94, 0.188, 0.13, 0.0, 0.833, 0.1, 0.5, 0.0],
        "w": [0.5, 0.5, 0.5, 0.5, 0.5, 0.5, 0.5, 0.5, 0.5, 0.5, 0.5, 0.5, 0.5, 0.5],
        "count": 13
    },
    "blackberry": {
        "x": [0.204, 0.311, 0.462, 0.062, 0.781, 0.182, 0.486, 0.287, 0.333, 1.0],
        "w": [0.5, 0.5, 0.5, 0.5, 0.5, 0.5, 0.5, 0.5, 0.5, 0.5],
        "count": 9
    },
    "lavender": {
        "x": [1.0, 0.257, 0.333, 0.389, 0.467, 1.0],
        "w": [0.51, 0.51, 0.51, 0.51, 0.51, 0.51],
        "count": 6
    },
    "liquorice": {
        "x": [0.75, 0.286, 0.812, 0.64, 0.409],
        "w": [0.5, 0.5, 0.5, 0.5, 0.5],
        "count": 5
    },
    "plum": {
        "x": [0.238, 0.74, 0.761, 0.111, 0.448, 0.032, 0.455, 0.444],
        "w": [0.56, 0.56, 0.56, 0.56, 0.56, 0.56, 0.56, 0.56],
        "count": 7
    },
    "cinnamon": {
        "x": [0.92, 0.81],
        "w": [0.5, 0.5],
        "count": 2
    },
    "graphite": {
        "x": [0.381, 0.667],
        "w": [0.75, 0.75],
        "count": 2
    },
    "fruity": {
        "x": [0.606, 0.357],
        "w": [0.5, 0.5],
        "count": 2
    },
    "strawberry": {
        "x": [0.742, 0.631],
        "w": [0.22, 0.75],
        "count": 2
    },
    "black tea": {
        "x": [0.26, 0.8],
        "w": [0.5, 0.5],
        "count": 2
    },
    "forest floor": {
        "x": [0.25, 0.875, 0.273],
        "w": [0.75, 0.75, 0.75],
        "count": 2
    },
    "mushroom": {
        "x": [0.235, 0.8, 0.69],
        "w": [0.75, 0.75, 0.75],
        "count": 3
    },
    "vanilla": {
        "x": [0.427, 0.844],
        "w": [0.5, 0.5],
        "count": 2
    },
    "oak": {
        "x": [0.152, 0.75, 0.667],
        "w": [0.75, 0.75, 0.75],
        "count": 3
    },
    "olive": {
        "x": [0.422, 0.6, 0.625],
        "w": [0.75, 0.75, 0.75],
        "count": 3
    },
    "cedar": {
        "x": [0.312, 0.323],
        "w": [0.75, 0.75],
        "count": 2
    }
}