{
    "honey": {
        "x": [0.779, 0.548, 0.14, 0.593, 0.852],
        "w": [0.5, 0.5, 0.5, 0.5, 0.5],
        "count": 4
    },
    "apricot": {
        "x": [0.744, 0.18, 0.0],
        "w": [0.5, 0.5, 0.5],
        "count": 3
    },
    "lemon": {
        "x": [0.919, 0.237, 0.22, 0.185],
        "w": [0.5, 0.5, 0.5, 0.5],
        "count": 4
    },
    "ripe": {
        "x": [0.056, 0.333],
        "w": [0.5, 0.5],
        "count": 2
    },
    "apple": {
        "x": [0.111, 0.26, 0.259],
        "w": [0.5, 0.5, 0.5],
        "count": 3
    }
}