{
    "cherry": {
        "x": [0.5, 0.591, 0.0, 0.204, 1.0, 0.161, 0.451, 0.0],
        "w": [0.61, 0.61, 0.61, 0.61, 0.61, 0.61, 0.61, 0.61],
        "count": 7
    },
    "plum": {
        "x": [0.621, 0.143, 0.417, 0.0],
        "w": [0.5, 0.5, 0.5, 0.5],
        "count": 4
    },
    "pepper": {
        "x": [0.773, 0.062, 0.923, 0.4, 0.237, 0.667, 0.5],
        "w": [0.5, 0.5, 0.5, 0.5, 0.5, 0.5, 0.5],
        "count": 7
    },
    "fruity": {
        "x": [0.25, 0.0, 0.0, 0.0],
        "w": [0.5, 0.5, 0.5, 0.5],
        "count": 4
    },
    "earthy": {
        "x": [0.429, 0.83, 0.667],
        "w": [0.5, 0.5, 0.5],
        "count": 3
    },
    "vanilla": {
        "x": [0.167, 0.571, 0.0],
        "w": [0.5, 0.5, 0.5],
        "count": 3
    },
    "violet": {
        "x": [0.975, 0.207],
        "w": [0.5, 0.5],
        "count": 2
    },
    "ripe": {
        "x": [0.42, 0.8],
        "w": [0.5, 0.5],
        "count": 2
    },
    "blackberry": {
        "x": [0.283, 0.497, 0.357],
        "w": [0.61, 0.61, 0.61],
        "count": 2
    },
    "oak": {
        "x": [0.143, 0.786],
        "w": [0.52, 0.52],
        "count": 2
    },
    "olive": {
        "x": [0.625, 0.242],
        "w": [0.52, 0.52],
        "count": 2
    },
    "leather": {
        "x": [0.333, 1.0],
        "w": [0.52, 0.1],
        "count": 2
    }
}