{
    "earthy": {
        "x": [1.0, 1.0, 1.0, 0.211, 0.684, 0.529, 0.429, 0.936, 1.0, 0.75],
        "w": [0.5, 0.5, 0.5, 0.5, 0.5, 0.5, 0.5, 0.5, 0.5, 0.5],
        "count": 9
    },
    "vanilla": {
        "x": [0.667, 0.0, 0.19, 0.67, 0.25, 0.824, 0.053, 0.667, 0.231, 0.5, 0.231, 0.176, 0.0, 0.182, 0.449, 0.778, 0.662, 0.656, 0.0, 1.0, 0.364],
        "w": [0.5, 0.5, 0.5, 0.5, 0.5, 0.5, 0.5, 0.5, 0.5, 0.5, 0.5, 0.5, 0.5, 0.5, 0.5, 0.5, 0.1, 0.5, 0.5, 0.5, 0.5],
        "count": 19
    },
    "oak": {
        "x": [0.833, 0.357, 0.643, 0.167, 0.333, 0.068, 0.195, 1.0, 0.381, 0.9, 0.8, 1.0, 0.853, 0.415, 0.979, 0.381, 0.353, 0.375, 0.0, 0.533, 0.719, 0.667, 0.6, 0.455, 0.85, 0.455],
        "w": [0.67, 0.67, 0.67, 0.67, 0.67, 0.67, 0.67, 0.67, 0.67, 0.67, 0.67, 0.67, 0.67, 0.13, 0.27, 0.67, 0.67, 0.67, 0.67, 0.67, 0.67, 0.67, 0.67, 0.67, 0.67, 0.67],
        "count": 22
    },
    "herbal": {
        "x": [0.5, 0.136, 0.039],
        "w": [0.5, 0.5, 0.5],
        "count": 3
    },
    "black fruit": {
        "x": [0.5, 0.4, 0.915, 0.941, 0.0, 0.412, 0.0, 0.667, 0.531, 0.0],
        "w": [0.5, 0.5, 0.5, 0.5, 0.5, 0.5, 0.5, 0.5, 0.5, 0.5],
        "count": 10
    },
    "mushroom": {
        "x": [0.833, 0.061, 0.263, 0.737, 0.615, 0.588, 0.571, 0.93, 0.959, 1.0],
        "w": [0.67, 0.67, 0.67, 0.67, 0.67, 0.67, 0.67, 0.67, 0.67, 0.67],
        "count": 8
    },
    "leather": {
        "x": [0.182, 0.955, 0.794, 0.583, 0.333, 0.615, 0.905, 0.945, 0.636],
        "w": [0.67, 0.67, 0.67, 0.67, 0.67, 0.67, 0.67, 0.67, 0.67],
        "count": 7
    },
    "floral": {
        "x": [0.909, 1.0],
        "w": [0.5, 0.5],
        "count": 2
    },
    "mineral": {
        "x": [1.0, 0.664],
        "w": [0.67, 0.67],
        "count": 2
    },
    "raspberry": {
        "x": [0.769, 0.182, 0.145, 0.56, 0.368, 1.0, 0.524, 0.925],
        "w": [0.71, 0.71, 0.71, 0.71, 0.71, 0.71, 0.71, 0.71],
        "count": 7
    },
    "cherry": {
        "x": [0.409, 0.225, 0.244, 0.355, 0.633, 0.122, 0.76, 0.2, 0.912, 0.158, 0.316, 0.632, 0.842, 0.122, 0.142, 0.5, 0.769, 0.676, 0.238, 0.294, 0.824, 0.941, 0.19, 0.286, 0.702, 0.333, 0.538, 0.952, 0.667, 0.2, 0.333, 0.4, 0.333, 0.273],
        "w": [0.71, 0.71, 0.71, 0.71, 0.71, 0.71, 0.71, 0.71, 0.71, 0.71, 0.71, 0.71, 0.71, 0.71, 0.71, 0.71, 0.71, 0.14, 0.71, 0.71, 0.71, 0.71, 0.71, 0.71, 0.71, 0.71, 0.71, 0.71, 0.71, 0.71, 0.71, 0.71, 0.71, 0.71],
        "count": 28
    },
    "blackberry": {
        "x": [0.0, 0.162, 0.293, 0.946, 0.638, 0.073, 0.038, 0.19, 0.167, 0.882, 0.286, 0.359, 0.385, 0.229, 0.667],
        "w": [0.5, 0.5, 0.5, 0.5, 0.5, 0.5, 0.5, 0.5, 0.5, 0.5, 0.5, 0.5, 0.5, 0.5, 0.5],
        "count": 15
    },
    "liquorice": {
        "x": [0.857, 0.268],
        "w": [0.1, 0.5],
        "count": 2
    },
    "thyme": {
        "x": [0.121, 1.0],
        "w": [0.5, 0.5],
        "count": 2
    },
    "chocolate": {
        "x": [0.242, 0.738, 0.22, 0.743, 0.366, 0.853, 0.789, 0.269, 0.75, 1.0, 0.346, 0.647, 0.458, 0.397, 0.92, 0.067, 0.545],
        "w": [0.5, 0.5, 0.5, 0.5, 0.5, 0.5, 0.5, 0.5, 0.5, 0.5, 0.5, 0.5, 0.5, 0.5, 0.5, 0.5, 0.5],
        "count": 16
    },
    "violet": {
        "x": [0.288, 0.295, 0.248, 0.271, 0.714, 0.631, 0.256],
        "w": [0.5, 0.5, 0.5, 0.5, 0.5, 0.5, 0.5],
        "count": 7
    },
    "coffee": {
        "x": [0.754, 0.627, 0.2],
        "w": [0.5, 0.1, 0.5],
        "count": 3
    },
    "ripe": {
        "x": [0.18, 0.22, 0.138, 0.0, 0.913, 0.195],
        "w": [0.5, 0.5, 0.5, 0.5, 0.5, 0.5],
        "count": 6
    },
    "cedar": {
        "x": [0.8, 0.664, 0.707, 0.439, 0.862, 0.333, 0.393, 0.423],
        "w": [0.2, 0.67, 0.67, 0.67, 0.67, 0.67, 0.67, 0.67],
        "count": 8
    },
    "graphite": {
        "x": [0.306, 0.857],
        "w": [0.67, 0.67],
        "count": 2
    },
    "plum": {
        "x": [0.189, 0.024, 0.196, 0.591, 0.265, 0.505, 0.156, 0.95, 0.603, 0.286, 0.206, 0.706, 0.25, 0.357, 0.8],
        "w": [0.53, 0.53, 0.53, 0.53, 0.53, 0.53, 0.53, 0.53, 0.53, 0.53, 0.53, 0.53, 0.53, 0.53, 0.53],
        "count": 12
    },
    "currant": {
        "x": [0.573, 0.306, 0.82, 0.615, 0.154, 0.286],
        "w": [0.71, 0.71, 0.71, 0.71, 0.71, 0.71],
        "count": 5
    },
    "tobacco": {
        "x": [0.645, 0.452],
        "w": [0.5, 0.5],
        "count": 2
    },
    "pepper": {
        "x": [0.81, 0.538, 0.667],
        "w": [0.5, 0.5, 0.5],
        "count": 3
    },
    "mocha": {
        "x": [1.0, 0.167],
        "w": [0.5, 0.5],
        "count": 2
    },
    "clove": {
        "x": [0.119, 0.476],
        "w": [0.5, 0.5],
        "count": 2
    },
    "cinnamon": {
        "x": [0.0, 1.0, 0.636],
        "w": [0.5, 0.5, 0.5],
        "count": 3
    }
}