{
    "orange peel": {
        "x": [0.0, 0.667, 0.264, 0.087, 0.931, 0.05],
        "w": [0.5, 0.5, 0.5, 0.5, 0.5, 0.5],
        "count": 3
    },
    "oak": {
        "x": [0.556, 0.694],
        "w": [0.5, 0.1],
        "count": 2
    },
    "butter": {
        "x": [0.714, 0.938],
        "w": [0.5, 0.5],
        "count": 2
    },
    "apple": {
        "x": [0.958, 0.818],
        "w": [0.5, 0.5],
        "count": 2
    },
    "mineral": {
        "x": [0.1, 0.591],
        "w": [0.5, 0.5],
        "count": 2
    }
}