{
    "leather": {
        "x": [0.963, 0.0, 0.444, 0.0, 0.2, 0.905, 0.0],
        "w": [0.5, 0.5, 0.5, 0.5, 0.5, 0.5, 0.5],
        "count": 6
    },
    "blackberry": {
        "x": [0.173, 0.76, 0.338, 0.931],
        "w": [0.5, 0.5, 0.5, 0.5],
        "count": 4
    },
    "cherry": {
        "x": [0.669, 0.88, 0.022, 0.179, 0.35],
        "w": [0.51, 0.51, 0.51, 0.51, 0.51],
        "count": 4
    },
    "oak": {
        "x": [0.062, 0.25, 0.8],
        "w": [0.5, 0.5, 0.5],
        "count": 3
    },
    "liquorice": {
        "x": [0.376, 0.467],
        "w": [0.5, 0.5],
        "count": 2
    },
    "strawberry": {
        "x": [0.5, 0.833],
        "w": [0.51, 0.51],
        "count": 2
    },
    "pepper": {
        "x": [0.667, 0.0, 0.924, 0.5],
        "w": [0.5, 0.5, 0.5, 0.5],
        "count": 4
    },
    "clove": {
        "x": [0.333, 0.945],
        "w": [0.5, 0.5],
        "count": 2
    },
    "black fruit": {
        "x": [0.0, 0.167],
        "w": [0.5, 0.5],
        "count": 2
    },
    "currant": {
        "x": [0.067, 0.232, 0.375],
        "w": [0.51, 0.51, 0.51],
        "count": 2
    },
    "prune": {
        "x": [0.717, 0.364],
        "w": [0.5, 0.5],
        "count": 2
    }
}