{
    "cherry": {
        "x": [0.294, 0.22, 0.292, 0.5, 0.0, 0.545, 0.0],
        "w": [0.5, 0.5, 0.5, 0.5, 0.5, 0.5, 0.5],
        "count": 7
    },
    "vanilla": {
        "x": [0.765, 1.0, 0.182],
        "w": [0.5, 0.5, 0.5],
        "count": 3
    },
    "oak": {
        "x": [0.941, 0.286, 0.0, 1.0, 0.0, 0.286, 0.091, 0.0],
        "w": [0.5, 0.5, 0.5, 0.5, 0.5, 0.5, 0.5, 0.5],
        "count": 8
    },
    "raspberry": {
        "x": [0.412, 0.0, 1.0, 0.0, 0.364],
        "w": [0.5, 0.5, 0.5, 0.5, 0.5],
        "count": 5
    },
    "pepper": {
        "x": [0.5, 0.333, 0.909, 0.944],
        "w": [0.5, 0.5, 0.5, 0.5],
        "count": 4
    },
    "leather": {
        "x": [0.667, 0.091],
        "w": [0.5, 0.5],
        "count": 2
    },
    "mushroom": {
        "x": [0.708, 0.571, 0.273],
        "w": [0.5, 0.5, 0.5],
        "count": 3
    }
}