{
    "green apple": {
        "x": [0.462, 0.583, 0.333, 0.63, 0.333, 0.113, 0.273],
        "w": [0.59, 0.59, 0.59, 0.59, 0.59, 0.59, 0.59],
        "count": 7
    },
    "lemon": {
        "x": [0.692, 0.6, 0.667, 0.229, 1.0, 0.305, 0.235, 0.057, 0.8],
        "w": [0.75, 0.75, 0.75, 0.3, 0.75, 0.75, 0.75, 0.75, 0.75],
        "count": 8
    },
    "citrus": {
        "x": [0.385, 0.068, 0.164, 0.156, 0.0, 0.593, 1.0, 0.111, 0.7, 0.0],
        "w": [0.5, 0.5, 0.5, 0.5, 0.5, 0.5, 0.5, 0.5, 0.5, 0.5],
        "count": 9
    },
    "pear": {
        "x": [0.615, 0.667, 0.602, 0.409],
        "w": [0.59, 0.59, 0.59, 0.59],
        "count": 4
    },
    "mineral": {
        "x": [0.722, 0.192, 0.995, 0.1, 0.714, 0.667, 0.229, 0.443, 0.82],
        "w": [0.5, 0.5, 0.5, 0.5, 0.5, 0.15, 0.5, 0.5, 0.5],
        "count": 7
    },
    "fruity": {
        "x": [0.5, 0.0, 0.4, 0.2],
        "w": [0.5, 0.5, 0.5, 0.5],
        "count": 4
    },
    "apple": {
        "x": [0.096, 0.545, 0.367, 0.189],
        "w": [0.59, 0.59, 0.59, 0.59],
        "count": 3
    },
    "apricot": {
        "x": [0.789, 0.889],
        "w": [0.59, 0.59],
        "count": 2
    },
    "peach": {
        "x": [1.0, 0.918],
        "w": [0.59, 0.59],
        "count": 2
    },
    "floral": {
        "x": [0.427, 0.04, 0.019, 0.5],
        "w": [0.5, 0.5, 0.5, 0.5],
        "count": 4
    },
    "smoke": {
        "x": [0.25, 1.0, 0.545, 0.46],
        "w": [0.5, 0.15, 0.5, 0.5],
        "count": 4
    },
    "tobacco": {
        "x": [0.4, 0.786],
        "w": [0.5, 0.5],
        "count": 2
    }
}