{
    "butter": {
        "x": [0.148, 0.594, 0.143, 0.833, 0.846],
        "w": [0.5, 0.5, 0.5, 0.5, 0.5],
        "count": 4
    },
    "pepper": {
        "x": [1.0, 0.455, 0.167, 0.25, 0.714],
        "w": [0.5, 0.5, 0.5, 0.5, 0.5],
        "count": 5
    },
    "oak": {
        "x": [0.82, 0.583, 1.0, 0.591, 0.0, 0.0, 1.0, 0.316, 0.169],
        "w": [0.17, 0.57, 0.57, 0.57, 0.57, 0.57, 0.57, 0.57, 0.57],
        "count": 9
    },
    "raspberry": {
        "x": [0.172, 0.0, 0.345, 0.945, 0.0, 0.783],
        "w": [0.75, 0.75, 0.75, 0.75, 0.75, 0.75],
        "count": 6
    },
    "fruity": {
        "x": [0.286, 0.0, 0.0, 0.0, 0.111, 1.0],
        "w": [0.15, 0.5, 0.5, 0.5, 0.5, 0.5],
        "count": 6
    },
    "strawberry": {
        "x": [0.565, 0.468, 0.575],
        "w": [0.75, 0.75, 0.75],
        "count": 3
    },
    "cut grass": {
        "x": [0.665, 0.662],
        "w": [0.57, 0.11],
        "count": 2
    },
    "chocolate": {
        "x": [0.761, 0.448],
        "w": [0.5, 0.5],
        "count": 2
    },
    "mineral": {
        "x": [0.333, 0.333],
        "w": [0.57, 0.57],
        "count": 2
    },
    "cherry": {
        "x": [1.0, 0.0, 0.6, 0.18, 0.178],
        "w": [0.75, 0.75, 0.75, 0.75, 0.75],
        "count": 5
    },
    "red fruit": {
        "x": [0.333, 0.537, 0.308],
        "w": [0.5, 0.5, 0.5],
        "count": 3
    },
    "earthy": {
        "x": [0.725, 1.0, 0.238],
        "w": [0.1, 0.5, 0.5],
        "count": 3
    },
    "plum": {
        "x": [0.21, 0.333],
        "w": [0.5, 0.15],
        "count": 2
    },
    "floral": {
        "x": [0.75, 0.0],
        "w": [0.5, 0.5],
        "count": 2
    }
}