{
    "strawberry": {
        "x": [0.259, 0.87, 0.0, 0.159, 0.891, 1.0, 0.365, 0.28, 0.194, 0.182, 0.2, 1.0, 0.836, 0.667],
        "w": [0.75, 0.75, 0.75, 0.75, 0.75, 0.75, 0.75, 0.75, 0.75, 0.75, 0.75, 0.75, 0.75, 0.75],
        "count": 13
    },
    "cherry": {
        "x": [0.232, 0.883, 0.928, 0.091, 0.882, 0.973, 0.778, 0.192, 0.267, 0.186, 0.136, 0.375, 0.5],
        "w": [0.75, 0.75, 0.75, 0.75, 0.75, 0.75, 0.75, 0.75, 0.75, 0.75, 0.75, 0.75, 0.75],
        "count": 10
    },
    "vanilla": {
        "x": [0.312, 0.091, 0.46, 0.303, 0.5, 0.918, 0.0],
        "w": [0.1, 0.5, 0.5, 0.5, 0.5, 0.5, 0.5],
        "count": 7
    },
    "pepper": {
        "x": [1.0, 0.409],
        "w": [0.5, 0.5],
        "count": 2
    },
    "fruity": {
        "x": [1.0, 0.25, 0.977, 0.5, 0.154, 1.0, 1.0],
        "w": [0.5, 0.5, 0.5, 0.15, 0.15, 0.15, 0.5],
        "count": 7
    },
    "red fruit": {
        "x": [0.705, 0.429, 0.067, 0.962, 0.541],
        "w": [0.5, 0.5, 0.5, 0.5, 0.5],
        "count": 5
    },
    "oak": {
        "x": [0.818, 0.156, 0.115, 0.82, 0.99],
        "w": [0.5, 0.5, 0.5, 0.5, 0.5],
        "count": 5
    },
    "raspberry": {
        "x": [0.9, 0.982, 0.6, 0.611, 0.571, 0.045, 0.462, 0.4, 0.097, 0.271, 1.0],
        "w": [0.75, 0.75, 0.75, 0.75, 0.75, 0.75, 0.75, 0.75, 0.75, 0.75, 0.75],
        "count": 10
    },
    "butter": {
        "x": [0.0, 0.182],
        "w": [0.5, 0.5],
        "count": 2
    },
    "leather": {
        "x": [0.524, 0.588],
        "w": [0.5, 0.5],
        "count": 2
    }
}