{
    "apple": {
        "x": [0.38, 0.667, 0.2, 0.604, 0.222, 0.244, 0.333, 0.575, 0.314, 0.0, 0.35, 1.0, 0.182, 0.182, 0.203, 0.95, 0.526, 0.676, 0.187, 0.568, 0.569, 0.148, 0.46],
        "w": [0.75, 0.75, 0.75, 0.75, 0.75, 0.75, 0.75, 0.75, 0.75, 0.75, 0.75, 0.75, 0.75, 0.75, 0.75, 0.75, 0.75, 0.75, 0.75, 0.75, 0.75, 0.75, 0.75],
        "count": 20
    },
    "citrus": {
        "x": [0.24, 0.648, 0.35, 0.6, 0.5, 0.556, 1.0, 0.35, 0.714, 0.474, 0.357, 0.45, 1.0, 0.636, 0.186, 0.385, 0.534, 0.077, 0.259, 0.269, 0.933, 1.0],
        "w": [0.5, 0.5, 0.5, 0.5, 0.5, 0.5, 0.5, 0.5, 0.5, 0.5, 0.5, 0.5, 0.15, 0.5, 0.5, 0.5, 0.5, 0.5, 0.5, 0.5, 0.5, 0.5],
        "count": 20
    },
    "floral": {
        "x": [0.16, 0.675, 0.733, 0.667, 0.39, 1.0, 0.222, 0.164, 0.78, 0.875, 1.0, 0.5, 0.114, 0.556, 0.292, 0.37, 0.25, 0.83, 0.0, 0.625, 1.0, 0.25, 0.625, 0.325, 0.102, 0.81, 0.286, 0.714, 0.571, 1.0, 0.211, 0.5, 0.357, 0.25, 0.6, 0.4, 0.125, 1.0],
        "w": [0.5, 0.5, 0.5, 0.5, 0.5, 0.5, 0.5, 0.5, 0.5, 0.5, 0.5, 0.5, 0.5, 0.5, 0.5, 0.5, 0.5, 0.5, 0.5, 0.5, 0.5, 0.5, 0.5, 0.5, 0.5, 0.5, 0.5, 0.5, 0.5, 0.5, 0.5, 0.5, 0.5, 0.5, 0.5, 0.5, 0.5, 0.5],
        "count": 36
    },
    "honey": {
        "x": [0.32, 0.545, 0.444, 0.333, 0.3, 0.727, 0.386, 0.529, 0.059, 0.638, 0.333, 0.25],
        "w": [0.5, 0.5, 0.5, 0.5, 0.5, 0.5, 0.5, 0.5, 0.5, 0.5, 0.5, 0.5],
        "count": 10
    },
    "grapefruit": {
        "x": [0.714, 0.412, 0.625, 0.989, 0.159, 0.454, 0.345, 1.0, 0.639, 0.625, 0.647, 0.571],
        "w": [0.75, 0.75, 0.75, 0.75, 0.15, 0.75, 0.75, 0.75, 0.75, 0.75, 0.75, 0.75],
        "count": 10
    },
    "ripe": {
        "x": [0.325, 0.771],
        "w": [0.5, 0.5],
        "count": 2
    },
    "fruity": {
        "x": [0.25, 0.933, 0.0, 0.0, 0.0, 0.0, 1.0, 0.082, 0.188, 1.0, 0.5, 0.833, 0.571, 0.143, 0.133, 0.0, 0.323, 0.056, 0.0, 1.0, 1.0, 0.898, 0.0, 0.0, 0.0, 1.0],
        "w": [0.5, 0.5, 0.5, 0.5, 0.5, 0.5, 0.15, 0.5, 0.5, 0.5, 0.5, 0.5, 0.5, 0.5, 0.5, 0.5, 0.5, 0.5, 0.5, 0.5, 0.5, 0.5, 0.5, 0.5, 0.5, 0.5],
        "count": 26
    },
    "tropical": {
        "x": [0.6, 0.625, 0.9, 0.108],
        "w": [0.5, 0.5, 0.5, 0.5],
        "count": 4
    },
    "tangerine": {
        "x": [0.4, 0.0],
        "w": [0.75, 0.75],
        "count": 2
    },
    "peach": {
        "x": [0.55, 0.176, 0.167, 0.893, 0.952, 0.222],
        "w": [0.75, 0.75, 0.75, 0.75, 0.75, 0.75],
        "count": 5
    },
    "lemon": {
        "x": [0.0, 0.294, 1.0, 0.075, 0.316, 0.625, 0.562, 0.292, 0.22, 0.207, 0.083, 0.625, 0.305, 0.963, 0.159, 0.583, 0.75, 0.438, 0.909, 0.75],
        "w": [0.75, 0.75, 0.75, 0.75, 0.75, 0.75, 0.75, 0.75, 0.75, 0.75, 0.75, 0.75, 0.75, 0.75, 0.75, 0.75, 0.75, 0.75, 0.75, 0.75],
        "count": 19
    },
    "green apple": {
        "x": [0.75, 0.0, 0.575, 0.438, 0.178, 0.0, 0.614, 0.887, 0.529, 0.917],
        "w": [0.75, 0.75, 0.75, 0.75, 0.75, 0.75, 0.75, 0.75, 0.75, 0.75],
        "count": 10
    },
    "pear": {
        "x": [0.0, 0.469, 0.0, 0.857, 0.421, 0.296, 0.25, 0.55, 0.364, 0.223, 0.274, 0.603, 0.185, 0.19, 0.5],
        "w": [0.75, 0.75, 0.75, 0.75, 0.75, 0.75, 0.75, 0.75, 0.75, 0.75, 0.75, 0.75, 0.75, 0.75, 0.75],
        "count": 15
    },
    "pineapple": {
        "x": [0.182, 0.362, 0.091, 1.0],
        "w": [0.75, 0.75, 0.75, 0.75],
        "count": 4
    },
    "lime": {
        "x": [0.364, 0.688, 1.0, 0.571, 0.614],
        "w": [0.75, 0.75, 0.75, 0.75, 0.75],
        "count": 5
    },
    "mineral": {
        "x": [0.529, 0.75, 0.75, 0.731, 0.321, 0.429, 0.118, 0.556, 0.286, 0.833, 0.625, 1.0, 0.5, 1.0, 1.0, 0.185, 1.0, 0.0, 0.444, 1.0, 0.714, 0.0, 0.762, 0.091, 0.0, 0.5, 0.714, 0.167, 0.571, 0.0, 1.0, 0.286, 0.75, 0.5],
        "w": [0.5, 0.5, 0.5, 0.5, 0.5, 0.5, 0.15, 0.5, 0.5, 0.5, 0.5, 0.5, 0.5, 0.5, 0.5, 0.5, 0.5, 0.5, 0.5, 0.5, 0.5, 0.5, 0.5, 0.5, 0.5, 0.5, 0.5, 0.5, 0.5, 0.5, 0.5, 0.5, 0.5, 0.5],
        "count": 34
    },
    "orange peel": {
        "x": [0.773, 0.914, 0.925, 0.963, 0.973],
        "w": [0.75, 0.75, 0.75, 0.75, 0.75],
        "count": 2
    },
    "guava": {
        "x": [0.857, 0.659],
        "w": [0.75, 0.75],
        "count": 2
    },
    "plum": {
        "x": [0.875, 0.686],
        "w": [0.5, 0.5],
        "count": 2
    },
    "banana": {
        "x": [0.3, 0.5],
        "w": [0.75, 0.75],
        "count": 2
    },
    "melon": {
        "x": [1.0, 0.235, 0.357, 1.0, 0.264, 0.292, 0.857, 0.412, 0.318],
        "w": [0.75, 0.75, 0.75, 0.75, 0.75, 0.75, 0.75, 0.75, 0.22],
        "count": 9
    },
    "almond": {
        "x": [0.0, 0.4, 0.588],
        "w": [0.5, 0.5, 0.5],
        "count": 3
    },
    "cut grass": {
        "x": [0.5, 1.0, 0.091, 0.13, 0.529, 1.0],
        "w": [0.5, 0.5, 0.5, 0.5, 0.5, 0.5],
        "count": 6
    },
    "stone": {
        "x": [0.6, 0.433, 0.633, 0.0, 0.156, 0.795, 0.143, 0.875],
        "w": [0.5, 0.5, 0.5, 0.5, 0.5, 0.5, 0.5, 0.5],
        "count": 8
    },
    "yeast": {
        "x": [0.464, 0.213],
        "w": [0.5, 0.5],
        "count": 2
    },
    "apricot": {
        "x": [0.248, 0.125, 0.542],
        "w": [0.75, 0.75, 0.75],
        "count": 3
    },
    "butter": {
        "x": [0.7, 0.37, 0.545],
        "w": [0.5, 0.5, 0.5],
        "count": 3
    }
}