{
    "smoke": {
        "x": [0.0, 0.0],
        "w": [0.5, 0.5],
        "count": 2
    },
    "blackberry": {
        "x": [0.333, 0.097, 0.667, 0.2, 0.182],
        "w": [0.63, 0.63, 0.63, 0.63, 0.63],
        "count": 5
    },
    "cherry": {
        "x": [0.0, 1.0, 0.602, 0.25, 0.681, 0.667],
        "w": [0.63, 0.13, 0.63, 0.63, 0.63, 0.63],
        "count": 6
    },
    "oak": {
        "x": [0.032, 0.226, 0.421, 0.361, 0.2],
        "w": [0.5, 0.5, 0.1, 0.5, 0.5],
        "count": 5
    },
    "raspberry": {
        "x": [0.833, 0.455, 0.158],
        "w": [0.63, 0.63, 0.63],
        "count": 3
    },
    "tobacco": {
        "x": [0.222, 0.184, 0.0, 0.267],
        "w": [0.5, 0.5, 0.5, 0.5],
        "count": 4
    },
    "chocolate": {
        "x": [0.0, 0.728, 0.305, 0.5, 0.357, 0.755],
        "w": [0.5, 0.5, 0.5, 0.5, 0.5, 0.5],
        "count": 6
    },
    "pepper": {
        "x": [0.444, 0.267, 0.686, 0.067],
        "w": [0.5, 0.5, 0.5, 0.5],
        "count": 3
    },
    "vanilla": {
        "x": [0.372, 0.278, 0.506],
        "w": [0.5, 0.5, 0.1],
        "count": 3
    },
    "liquorice": {
        "x": [0.0, 1.0],
        "w": [0.5, 0.1],
        "count": 2
    },
    "fruity": {
        "x": [0.944, 0.243, 0.0, 0.0],
        "w": [0.5, 0.5, 0.5, 0.5],
        "count": 4
    },
    "currant": {
        "x": [0.389, 0.908],
        "w": [0.63, 0.63],
        "count": 2
    },
    "plum": {
        "x": [0.556, 0.314, 0.427, 0.216, 0.364],
        "w": [0.5, 0.5, 0.5, 0.5, 0.5],
        "count": 5
    },
    "leather": {
        "x": [0.591, 0.714],
        "w": [0.5, 0.5],
        "count": 2
    }
}