{
    "ripe": {
        "x": [0.075, 0.127, 0.287, 0.104, 0.0],
        "w": [0.5, 0.5, 0.5, 0.5, 0.5],
        "count": 5
    },
    "cherry": {
        "x": [0.132, 0.175, 0.25, 0.8, 0.25, 0.271, 0.15, 0.127, 0.5, 0.5, 0.264, 0.156, 0.0, 0.455, 0.64, 0.576, 0.912, 0.333, 0.105, 0.158, 0.413, 0.577, 0.188, 0.264, 0.877, 0.833, 0.333, 0.594, 0.875, 0.111, 0.636, 0.5],
        "w": [0.75, 0.75, 0.75, 0.75, 0.75, 0.75, 0.22, 0.75, 0.75, 0.75, 0.75, 0.75, 0.75, 0.75, 0.75, 0.75, 0.75, 0.75, 0.75, 0.75, 0.75, 0.75, 0.75, 0.75, 0.75, 0.75, 0.75, 0.75, 0.75, 0.75, 0.75, 0.75],
        "count": 26
    },
    "strawberry": {
        "x": [0.094, 0.384, 0.25, 0.167, 0.167, 0.2, 0.0, 0.273, 0.885, 0.286, 0.656, 1.0],
        "w": [0.75, 0.75, 0.75, 0.75, 0.75, 0.75, 0.75, 0.75, 0.75, 0.75, 0.75, 0.75],
        "count": 12
    },
    "violet": {
        "x": [0.3, 0.925, 0.545, 1.0],
        "w": [0.52, 0.52, 0.52, 0.52],
        "count": 4
    },
    "smoke": {
        "x": [0.425, 0.285, 0.195],
        "w": [0.5, 0.5, 0.5],
        "count": 3
    },
    "raspberry": {
        "x": [0.138, 0.306, 0.211, 1.0],
        "w": [0.75, 0.75, 0.75, 0.75],
        "count": 4
    },
    "plum": {
        "x": [0.213, 0.562, 0.6, 0.156, 0.905],
        "w": [0.58, 0.58, 0.58, 0.58, 0.58],
        "count": 5
    },
    "earthy": {
        "x": [0.475, 0.716, 0.0, 0.0, 0.08, 0.267, 0.781, 0.75, 0.0],
        "w": [0.5, 0.5, 0.5, 0.5, 0.5, 0.5, 0.5, 0.5, 0.5],
        "count": 8
    },
    "pepper": {
        "x": [0.35, 0.232, 1.0, 0.218, 0.0, 0.743, 0.5, 1.0],
        "w": [0.5, 0.5, 0.5, 0.5, 0.5, 0.5, 0.5, 0.5],
        "count": 8
    },
    "clove": {
        "x": [0.45, 0.737, 0.273, 0.591, 1.0, 1.0],
        "w": [0.5, 0.5, 0.5, 0.5, 0.5, 0.5],
        "count": 6
    },
    "leather": {
        "x": [0.365, 0.289, 0.4, 0.5, 0.375, 0.159, 0.219, 0.0, 0.427, 0.7, 0.375, 0.932, 0.2, 0.0],
        "w": [0.75, 0.75, 0.15, 0.75, 0.75, 0.75, 0.75, 0.75, 0.75, 0.75, 0.22, 0.75, 0.75, 0.75],
        "count": 14
    },
    "black fruit": {
        "x": [0.418, 0.72],
        "w": [0.5, 0.5],
        "count": 2
    },
    "tobacco": {
        "x": [0.455, 0.807, 0.345, 0.947, 0.947, 1.0],
        "w": [0.5, 0.5, 0.5, 0.5, 0.5, 0.5],
        "count": 6
    },
    "fruity": {
        "x": [0.612, 0.0, 0.0, 0.167, 0.8, 1.0, 0.056, 0.684, 0.143, 0.0],
        "w": [0.5, 0.5, 0.5, 0.5, 0.5, 0.5, 0.5, 0.5, 0.5, 0.5],
        "count": 10
    },
    "floral": {
        "x": [0.933, 0.625, 0.456, 0.25],
        "w": [0.5, 0.5, 0.5, 0.5],
        "count": 4
    },
    "currant": {
        "x": [0.0, 0.182, 0.182, 0.2, 0.474],
        "w": [0.75, 0.75, 0.75, 0.75, 0.75],
        "count": 5
    },
    "blackberry": {
        "x": [0.125, 0.194, 0.455, 0.318, 0.667, 0.6, 0.333],
        "w": [0.75, 0.75, 0.75, 0.75, 0.75, 0.75, 0.75],
        "count": 7
    },
    "cinnamon": {
        "x": [0.785, 0.92],
        "w": [0.5, 0.5],
        "count": 2
    },
    "mushroom": {
        "x": [0.183, 0.25, 0.824, 0.053, 0.091],
        "w": [0.75, 0.75, 0.75, 0.75, 0.75],
        "count": 5
    },
    "brett": {
        "x": [0.012, 0.071, 0.12],
        "w": [0.15, 0.5, 0.5],
        "count": 3
    },
    "cedar": {
        "x": [0.278, 0.545],
        "w": [0.75, 0.75],
        "count": 2
    },
    "red fruit": {
        "x": [0.4, 0.833, 0.091, 0.0],
        "w": [0.5, 0.5, 0.5, 0.5],
        "count": 4
    },
    "pine": {
        "x": [0.357, 0.75],
        "w": [0.75, 0.75],
        "count": 2
    },
    "chocolate": {
        "x": [0.25, 0.438],
        "w": [0.5, 0.5],
        "count": 2
    },
    "yeast": {
        "x": [0.018, 1.0, 0.133],
        "w": [0.5, 0.5, 0.5],
        "count": 2
    },
    "liquorice": {
        "x": [0.236, 0.645, 1.0],
        "w": [0.5, 0.5, 0.5],
        "count": 3
    },
    "oak": {
        "x": [0.564, 0.278],
        "w": [0.75, 0.75],
        "count": 2
    }
}