{
    "apple": {
        "x": [0.412, 0.333, 0.348],
        "w": [0.53, 0.53, 0.53],
        "count": 3
    },
    "citrus": {
        "x": [0.706, 0.444, 0.572, 0.643, 0.529],
        "w": [0.2, 0.5, 0.1, 0.5, 0.5],
        "count": 5
    },
    "fruity": {
        "x": [0.0, 1.0, 0.4],
        "w": [0.5, 0.5, 0.5],
        "count": 3
    },
    "peach": {
        "x": [0.529, 0.762, 0.389, 1.0, 0.0, 0.217, 0.643, 0.25],
        "w": [0.53, 0.53, 0.53, 0.53, 0.53, 0.53, 0.21, 0.16],
        "count": 8
    },
    "apricot": {
        "x": [0.235, 1.0, 0.5, 0.0, 0.262, 0.184, 0.793],
        "w": [0.11, 0.53, 0.53, 0.53, 0.53, 0.53, 0.53],
        "count": 7
    },
    "butterscotch": {
        "x": [1.0, 0.333],
        "w": [0.1, 0.5],
        "count": 2
    },
    "lime": {
        "x": [0.619, 0.905, 0.379],
        "w": [0.71, 0.71, 0.71],
        "count": 2
    },
    "pineapple": {
        "x": [0.524, 0.0, 0.583, 0.478, 0.505, 0.0],
        "w": [0.53, 0.53, 0.11, 0.53, 0.53, 0.53],
        "count": 6
    },
    "oak": {
        "x": [0.238, 0.722, 0.173, 0.791, 1.0, 0.714],
        "w": [0.5, 0.5, 0.5, 0.1, 0.5, 0.5],
        "count": 5
    },
    "butter": {
        "x": [0.778, 0.519, 1.0, 0.96],
        "w": [0.5, 0.15, 0.5, 0.5],
        "count": 4
    },
    "stone": {
        "x": [0.111, 0.91, 0.586],
        "w": [0.5, 0.5, 0.1],
        "count": 3
    },
    "floral": {
        "x": [1.0, 0.646, 0.714],
        "w": [0.5, 0.5, 0.5],
        "count": 3
    },
    "tropical": {
        "x": [0.25, 0.31],
        "w": [0.5, 0.5],
        "count": 2
    },
    "ripe": {
        "x": [0.218, 0.439, 0.304],
        "w": [0.5, 0.5, 0.5],
        "count": 2
    },
    "banana": {
        "x": [0.321, 0.565],
        "w": [0.53, 0.53],
        "count": 2
    },
    "rose": {
        "x": [0.41, 0.429],
        "w": [0.11, 0.53],
        "count": 2
    }
}